{
  "id": "@artifactId@-@version@",
  "name": "MARCcat",
  "requires": [
    {
      "id": "configuration",
      "version": "2.0"
    }
  ],
  "provides": [
    {
      "id": "marccat",
      "version": "2.2",
      "handlers": [
        {
          "methods": [
            "GET"
          ],
          "pathPattern": "/marccat/search",
          "modulePermissions": [
            "configuration.entries.collection.get"
          ],
          "permissionsRequired": [
            "marccat.search.collection.get"
          ]
        },
        {
          "methods": [
            "GET"
          ],
          "pathPattern": "/marccat/searchAuth",
          "permissionsRequired": [
            "marccat.authority.collection.get"
          ]
        },
        {
          "methods": [
            "GET"
          ],
          "pathPattern": "/marccat/mergedSearch",
          "modulePermissions": [
            "configuration.entries.collection.get"
          ],
          "permissionsRequired": [
            "marccat.mergedSearch.collection.get"
          ]
        },
        {
          "methods": [
            "GET"
          ],
          "pathPattern": "/marccat/searchVertical",
          "modulePermissions": [
            "configuration.entries.collection.get"
          ],
          "permissionsRequired": [
            "marccat.searchVertical.collection.get"
          ]
        },
        {
          "methods": [
            "GET"
          ],
          "pathPattern": "/marccat/countSearch",
          "modulePermissions": [
            "configuration.entries.collection.get"
          ],
          "permissionsRequired": [
            "marccat.countSearch.item.get"
          ]
        },
        {
          "methods": [
            "GET"
          ],
          "pathPattern": "/marccat/document-count-by-id",
          "modulePermissions": [
            "configuration.entries.collection.get"
          ],
          "permissionsRequired": [
            "marccat.document-count-by-id.item.get"
          ]
        },
        {
          "methods": [
            "GET"
          ],
          "pathPattern": "/marccat/bibliographic/fields/mandatory",
          "modulePermissions": [
            "configuration.entries.collection.get"
          ],
          "permissionsRequired": [
            "marccat.bibliographic.fields.mandatory.collection.get"
          ]
        },
        {
          "methods": [
            "GET"
          ],
          "pathPattern": "/marccat/field-template",
          "modulePermissions": [
            "configuration.entries.collection.get"
          ],
          "permissionsRequired": [
            "marccat.field-template.item.get"
          ]
        },
        {
          "methods": [
            "GET"
          ],
          "pathPattern": "/marccat/browse",
          "modulePermissions": [
            "configuration.entries.collection.get"
          ],
          "permissionsRequired": [
            "marccat.browse.collection.get"
          ]
        },
        {
          "methods": [
            "GET"
          ],
          "pathPattern": "/marccat/next-page",
          "modulePermissions": [
            "configuration.entries.collection.get"
          ],
          "permissionsRequired": [
            "marccat.next-page.collection.get"
          ]
        },
        {
          "methods": [
            "GET"
          ],
          "pathPattern": "/marccat/previous-page",
          "modulePermissions": [
            "configuration.entries.collection.get"
          ],
          "permissionsRequired": [
            "marccat.previous-page.collection.get"
          ]
        },
        {
          "methods": [
            "GET"
          ],
          "pathPattern": "/marccat/headings-by-tag",
          "modulePermissions": [
            "configuration.entries.collection.get"
          ],
          "permissionsRequired": [
            "marccat.headings-by-tag.collection.get"
          ]
        },
        {
          "methods": [
            "GET"
          ],
          "pathPattern": "/marccat/filteredTagsList",
          "modulePermissions": [
            "configuration.entries.collection.get"
          ],
          "permissionsRequired": [
            "marccat.filteredTagsList.collection.get"
          ]
        },
        {
          "methods": [
            "GET"
          ],
          "pathPattern": "/marccat/filteredTag",
          "modulePermissions": [
            "configuration.entries.collection.get"
          ],
          "permissionsRequired": [
            "marccat.filteredTag.item.get"
          ]
        },
        {
          "methods": [
            "GET"
          ],
          "pathPattern": "/marccat/validateTag",
          "modulePermissions": [
            "configuration.entries.collection.get"
          ],
          "permissionsRequired": [
            "marccat.validateTag.item.get"
          ]
        },
        {
          "methods": [
            "GET"
          ],
          "pathPattern": "/marccat/record-templates",
          "modulePermissions": [
            "configuration.entries.collection.get"
          ],
          "permissionsRequired": [
            "marccat.record-templates.collection.get"
          ]
        },
        {
          "methods": [
            "GET"
          ],
          "pathPattern": "/marccat/record-template/{id}",
          "modulePermissions": [
            "configuration.entries.collection.get"
          ],
          "permissionsRequired": [
            "marccat.record-template.item.get"
          ]
        },
        {
          "methods": [
            "POST"
          ],
          "pathPattern": "/marccat/record-template",
          "modulePermissions": [
            "configuration.entries.collection.get"
          ],
          "permissionsRequired": [
            "marccat.record-template.item.post"
          ]
        },
        {
          "methods": [
            "PUT"
          ],
          "pathPattern": "/marccat/record-template/{id}",
          "modulePermissions": [
            "configuration.entries.collection.get"
          ],
          "permissionsRequired": [
            "marccat.record-template.item.put"
          ]
        },
        {
          "methods": [
            "POST"
          ],
          "pathPattern": "/marccat/record-template/from-record",
          "modulePermissions": [
            "configuration.entries.collection.get"
          ],
          "permissionsRequired": [
            "marccat.record-template.from-record.item.post"
          ]
        },
        {
          "methods": [
            "DELETE"
          ],
          "pathPattern": "/marccat/record-template/{id}",
          "modulePermissions": [
            "configuration.entries.collection.get"
          ],
          "permissionsRequired": [
            "marccat.record-template.item.delete"
          ]
        },
        {
          "methods": [
            "POST"
          ],
          "pathPattern": "/marccat/authority-record",
          "permissionsRequired": [
            "marccat.authority.insert.post"
          ]
        },
        {
          "methods": [
            "POST"
          ],
          "pathPattern": "/marccat/bibliographic-record",
          "modulePermissions": [
            "configuration.entries.collection.get"
          ],
          "permissionsRequired": [
            "marccat.bibliographic-record.item.post"
          ]
        },
        {
          "methods": [
            "GET"
          ],
          "pathPattern": "/marccat/bibliographic-record/{id}",
          "modulePermissions": [
            "configuration.entries.collection.get"
          ],
          "permissionsRequired": [
            "marccat.bibliographic-record.item.get"
          ]
        },
        {
          "methods": [
            "DELETE"
          ],
          "pathPattern": "/marccat/bibliographic-record/{id}",
          "modulePermissions": [
            "configuration.entries.collection.get"
          ],
          "permissionsRequired": [
            "marccat.bibliographic-record.item.delete"
          ]
        },
        {
          "methods": [
            "GET"
          ],
          "pathPattern": "/marccat/authority-record/from-template/{idTemplate}",
          "modulePermissions": [
            "configuration.entries.collection.get"
          ],
          "permissionsRequired": [
            "marccat.authority-record.from-template.item.get"
          ]
        },
        {
          "methods": [
            "GET"
          ],
          "pathPattern": "/marccat/bibliographic-record/from-template/{idTemplate}",
          "modulePermissions": [
            "configuration.entries.collection.get"
          ],
          "permissionsRequired": [
            "marccat.bibliographic-record.from-template.item.get"
          ]
        },
        {
          "methods": [
            "GET"
          ],
          "pathPattern": "/marccat/bibliographic-record/duplicate",
          "modulePermissions": [
            "configuration.entries.collection.get"
          ],
          "permissionsRequired": [
            "marccat.bibliographic-record.duplicate.item.get"
          ]
        },
        {
          "methods": [
            "POST"
          ],
          "pathPattern": "/marccat/bibliographic-record/fixed-field-display-value",
          "modulePermissions": [
            "configuration.entries.collection.get"
          ],
          "permissionsRequired": [
            "marccat.bibliographic-record.fixed-field-display-value.item.post"
          ]
        },
        {
          "methods": [
            "GET"
          ],
          "pathPattern": "/marccat/fixed-fields-code-groups-by-leader",
          "modulePermissions": [
            "configuration.entries.collection.get"
          ],
          "permissionsRequired": [
            "marccat.fixed-fields-code-groups-by-leader.collection.get"
          ]
        },
        {
          "methods": [
            "GET"
          ],
          "pathPattern": "/marccat/fixed-fields-code-groups",
          "modulePermissions": [
            "configuration.entries.collection.get"
          ],
          "permissionsRequired": [
            "marccat.fixed-fields-code-groups.collection.get"
          ]
        },
        {
          "methods": [
            "GET"
          ],
          "pathPattern": "/marccat/header-types",
          "modulePermissions": [
            "configuration.entries.collection.get"
          ],
          "permissionsRequired": [
            "marccat.header-types.collection.get"
          ]
        },
        {
          "methods": [
            "POST"
          ],
          "pathPattern": "/marccat/create-heading",
          "modulePermissions": [
            "configuration.entries.collection.get"
          ],
          "permissionsRequired": [
            "marccat.create-heading.item.post"
          ]
        },
        {
          "methods": [
            "POST"
          ],
          "pathPattern": "/marccat/load-from-file",
          "modulePermissions": [
            "configuration.entries.collection.get"
          ],
          "permissionsRequired": [
            "marccat.load-from-file.collection.post"
          ]
        },
        {
          "methods": [
            "PUT"
          ],
          "pathPattern": "/marccat/bibliographic-record/lock/{id}",
          "modulePermissions": [
            "configuration.entries.collection.get"
          ],
          "permissionsRequired": [
            "marccat.bibliographic-record.lock.item.put"
          ]
        },
        {
          "methods": [
            "DELETE"
          ],
          "pathPattern": "/marccat/bibliographic-record/unlock/{id}",
          "modulePermissions": [
            "configuration.entries.collection.get"
          ],
          "permissionsRequired": [
            "marccat.bibliographic-record.unlock.item.delete"
          ]
        }
      ]
    },
    {
      "id": "_tenant",
      "version": "1.2",
      "interfaceType": "system",
      "handlers": [
        {
          "methods": [
            "POST"
          ],
          "pathPattern": "/_/tenant"
        },
        {
          "methods": [
            "DELETE"
          ],
          "pathPattern": "/_/tenant"
        }
      ]
    }
  ],
  "permissionSets": [
    {
      "permissionName": "marccat.search.collection.get",
      "displayName": "marccat - get bibliographic or authority record collection",
      "description": "Get bibliographic or authority record collection"
    },
    {
      "permissionName": "marccat.mergedSearch.collection.get",
      "displayName": "marccat - get bibliographic and authority record collection",
      "description": "Get bibliographic and authority record collection"
    },
    {
      "permissionName": "marccat.searchVertical.collection.get",
      "displayName": "marccat - get vertical record collection",
      "description": "Get vertical record collection"
    },
    {
      "permissionName": "marccat.countSearch.item.get",
      "displayName": "marccat - get count record",
      "description": "Get count record"
    },
    {
      "permissionName": "marccat.document-count-by-id.item.get",
      "displayName": "marccat - get count record by id authority",
      "description": "Get count record by id authority"
    },
    {
      "permissionName": "marccat.bibliographic.fields.mandatory.collection.get",
      "displayName": "marccat - get mandatory tag collection",
      "description": "Get mandatory tag collection"
    },
    {
      "permissionName": "marccat.field-template.item.get",
      "displayName": "marccat - get individual field template",
      "description": "Get individual field template"
    },
    {
      "permissionName": "marccat.browse.collection.get",
      "displayName": "marccat - get heading collection",
      "description": "Get heading collection"
    },
    {
      "permissionName": "marccat.next-page.collection.get",
      "displayName": "marccat - get next page heading collection",
      "description": "Get next page of heading collection"
    },
    {
      "permissionName": "marccat.previous-page.collection.get",
      "displayName": "marccat - get previous page heading collection",
      "description": "Get previous page heading collection"
    },
    {
      "permissionName": "marccat.headings-by-tag.collection.get",
      "displayName": "marccat - get heading collection by tag",
      "description": "Get heading collection by tag"
    },
    {
      "permissionName": "marccat.filteredTagsList.collection.get",
      "displayName": "marccat - get filtered tag collection",
      "description": "Get filtered tag collection"
    },
    {
      "permissionName": "marccat.filteredTag.item.get",
      "displayName": "marccat - get filtered tag",
      "description": "Get filtered tag"
    },
    {
      "permissionName": "marccat.validateTag.item.get",
      "displayName": "marccat - get valid tag",
      "description": "Get valid tag"
    },
    {
      "permissionName": "marccat.record-templates.collection.get",
      "displayName": "marccat - get template collection",
      "description": "Get template collection"
    },
    {
      "permissionName": "marccat.record-template.item.get",
      "displayName": "marccat - get individual template",
      "description": "Get individual template"
    },
    {
      "permissionName": "marccat.record-template.item.post",
      "displayName": "marccat - create individual template",
      "description": "Create individual template"
    },
    {
      "permissionName": "marccat.record-template.item.put",
      "displayName": "marccat - modify template",
      "description": "Modify template"
    },
    {
      "permissionName": "marccat.record-template.from-record.item.post",
      "displayName": "marccat - get template from record",
      "description": "Get template from record"
    },
    {
      "permissionName": "marccat.record-template.item.delete",
      "displayName": "marccat - delete individual template",
      "description": "Delete individual template"
    },
    {
      "permissionName": "marccat.bibliographic-record.item.post",
      "displayName": "marccat - create individual bibliographic record",
      "description": "Create individual bibliographic record"
    },
    {
      "permissionName": "marccat.bibliographic-record.item.get",
      "displayName": "marccat - get individual bibliographic record",
      "description": "Get individual bibliographic record"
    },
    {
      "permissionName": "marccat.bibliographic-record.item.delete",
      "displayName": "marccat - delete individual bibliographic record",
      "description": "Delete individual bibliographic record"
    },
    {
      "permissionName": "marccat.bibliographic-record.from-template.item.get",
      "displayName": "marccat - get bibliographic record from template",
      "description": "Get bibliographic record from template"
    },
    {
      "permissionName": "marccat.authority-record.from-template.item.get",
      "displayName": "marccat - get authority record from template",
      "description": "Get authority record from template"
    },
    {
      "permissionName": "marccat.bibliographic-record.duplicate.item.get",
      "displayName": "marccat - get duplicate bibliographic record",
      "description": "Get duplicate bibliographic record"
    },
    {
      "permissionName": "marccat.bibliographic-record.fixed-field-display-value.item.post",
      "displayName": "marccat - get fixed field display value",
      "description": "Get fixed field display value"
    },
    {
      "permissionName": "marccat.fixed-fields-code-groups-by-leader.collection.get",
      "displayName": "marccat - get dropdown collection for fixed field by leader",
      "description": "Get dropdown collection for fixed field by leader"
    },
    {
      "permissionName": "marccat.fixed-fields-code-groups.collection.get",
      "displayName": "marccat - get dropdown collection for fixed field",
      "description": "Get dropdown collection for fixed field"
    },
    {
      "permissionName": "marccat.header-types.collection.get",
      "displayName": "marccat - get header type collection",
      "description": "Get header type collection"
    },
    {
      "permissionName": "marccat.create-heading.item.post",
      "displayName": "marccat - create individual heading",
      "description": "Create individual heading"
    },
    {
      "permissionName": "marccat.load-from-file.collection.post",
      "displayName": "marccat - load record collection from file",
      "description": "Load record collection from file"
    },
    {
      "permissionName": "marccat.bibliographic-record.lock.item.put",
      "displayName": "marccat - lock record",
      "description": ":Lock record"
    },
    {
      "permissionName": "marccat.bibliographic-record.unlock.item.delete",
      "displayName": "marccat - unlock record",
      "description": "Unlock record"
    },
    {
      "permissionName": "marccat.authority.collection.get",
      "displayName": "MARCcat - get authority collection",
      "description": "Get MARC authority record collection"
    },
    {
      "permissionName": "marccat.authority.insert.post",
      "displayName": "MARCcat - save authority record",
      "description": "Save MARC authority record"
    },
    {
      "permissionName": "marccat.all",
      "displayName": "marccat - all permissions",
      "description": "Entire set of permissions needed to use the marccat",
      "subPermissions": [
        "marccat.authority.insert.post",
        "marccat.authority.collection.get",
        "marccat.search.collection.get",
        "marccat.mergedSearch.collection.get",
        "marccat.searchVertical.collection.get",
        "marccat.countSearch.item.get",
        "marccat.document-count-by-id.item.get",
        "marccat.bibliographic.fields.mandatory.collection.get",
        "marccat.field-template.item.get",
        "marccat.browse.collection.get",
        "marccat.next-page.collection.get",
        "marccat.previous-page.collection.get",
        "marccat.headings-by-tag.collection.get",
        "marccat.filteredTagsList.collection.get",
        "marccat.filteredTag.item.get",
        "marccat.validateTag.item.get",
        "marccat.record-templates.collection.get",
        "marccat.record-template.item.get",
        "marccat.record-template.item.post",
        "marccat.record-template.item.put",
        "marccat.record-template.from-record.item.post",
        "marccat.record-template.item.delete",
        "marccat.bibliographic-record.item.post",
        "marccat.bibliographic-record.item.get",
        "marccat.bibliographic-record.item.delete",
        "marccat.bibliographic-record.from-template.item.get",
        "marccat.authority-record.from-template.item.get",
        "marccat.bibliographic-record.duplicate.item.get",
        "marccat.bibliographic-record.fixed-field-display-value.item.post",
        "marccat.fixed-fields-code-groups-by-leader.collection.get",
        "marccat.fixed-fields-code-groups.collection.get",
        "marccat.header-types.collection.get",
        "marccat.create-heading.item.post",
        "marccat.load-from-file.collection.post",
        "marccat.bibliographic-record.lock.item.put",
        "marccat.bibliographic-record.unlock.item.delete"
      ]
    }
  ],
  "launchDescriptor": {
    "dockerImage": "@artifactId@:@version@",
    "dockerPull": false,
    "dockerArgs": {
      "HostConfig": {
        "Memory": 872415232,
        "PortBindings": {
          "8081/tcp": [
            {
              "HostPort": "%p"
            }
          ]
        }
      }
    },
    "env": [
      {
        "name": "JAVA_OPTIONS",
        "value": "-XX:MaxRAMPercentage=66.0"
      },
      {
        "name": "DB_HOST",
        "value": "postgres"
      },
      {
        "name": "DB_PORT",
        "value": "5432"
      },
      {
        "name": "DB_USERNAME",
        "value": "folio_admin"
      },
      {
        "name": "DB_PASSWORD",
        "value": "folio_admin"
      },
      {
        "name": "DB_DATABASE",
        "value": "okapi_modules"
      },
      {
        "name": "DB_QUERYTIMEOUT",
        "value": "60000"
      },
      {
        "name": "DB_CHARSET",
        "value": "UTF-8"
      },
      {
        "name": "DB_MAXPOOLSIZE",
        "value": "5"
      }
    ]
  }
}
